jplotlib/__init__.py
jplotlib/grid_plot.py
jplotlib-1.0.2.dist-info/LICENSE
jplotlib-1.0.2.dist-info/METADATA
jplotlib-1.0.2.dist-info/WHEEL
jplotlib-1.0.2.dist-info/top_level.txt
jplotlib-1.0.2.dist-info/RECORD
