Metadata-Version: 2.1
Name: jplotlib
Version: 1.0.2
Summary: Simple plotting utilities
Home-page: https://github.com/JacobFV/jplotlib
Author: Jacob Valdez
Author-email: jacobfv@msn.com
License: UNKNOWN
Platform: UNKNOWN
Classifier: Programming Language :: Python :: 3
Classifier: License :: OSI Approved :: MIT License
Classifier: Operating System :: OS Independent
Requires-Python: >=3.6
